simplesecretsmanager/__init__.py
simplesecretsmanager/errors.py
simplesecretsmanager/manager.py
simplesecretsmanager/utility.py
simplesecretsmanager-0.6.2.dist-info/LICENSE
simplesecretsmanager-0.6.2.dist-info/METADATA
simplesecretsmanager-0.6.2.dist-info/WHEEL
simplesecretsmanager-0.6.2.dist-info/RECORD
