Metadata-Version: 2.1
Name: simplesecretsmanager
Version: 0.6.2
Summary: A simple secrets manager
License: MIT
Author: Bartowski
Requires-Python: >=3.10,<4.0
Classifier: License :: OSI Approved :: MIT License
Classifier: Programming Language :: Python :: 3
Classifier: Programming Language :: Python :: 3.10
Classifier: Programming Language :: Python :: 3.11
Requires-Dist: argon2-cffi (>=23.1.0,<24.0.0)
Requires-Dist: bcrypt (>=4.0.1,<5.0.0)
Requires-Dist: cryptography (>=39.0.2,<40.0.0)
Requires-Dist: pydantic (>=2.2.1,<3.0.0)
